{
  "faces": {
    "top": ["top", "up", "上", "上面", "頂部", "顶部", "+y", "y+"],
    "bottom": ["bottom", "down", "下", "下面", "底", "底部", "-y", "y-"],
    "left": ["left", "左", "左側", "左侧", "-x", "x-"],
    "right": ["right", "右", "右側", "右侧", "+x", "x+"],
    "front": ["front", "前", "前面", "+z", "z+"],
    "back": ["back", "後", "后", "後面", "后面", "-z", "z-"]
  },
  "methods": {
    "object_aabb": ["object aabb", "object_aabb", "obj aabb", "whole object", "物件aabb", "对象aabb"],
    "geometry_aabb": ["geometry aabb", "geometry_aabb", "mesh aabb", "geo aabb", "幾何aabb", "几何aabb"],
    "planar_cluster": ["planar cluster", "planar_cluster", "平面分群", "平面聚類", "平面聚类"],
    "obb_pca": ["obb", "pca", "obb pca", "obb_pca"],
    "picked": ["picked", "pick face", "clicked face", "手動選面", "手动选面"],
    "auto": ["auto", "自動", "自动"]
  },
  "mateModeTokens": {
    "both": ["both", "arc", "insert", "cover", "插入", "蓋上", "盖上", "弧線", "弧线"],
    "twist": ["twist", "rotate", "旋轉", "旋转"],
    "translate": ["translate", "move only", "平移", "只移動", "只移动"]
  },
  "sourceTarget": {
    "sourceKeywords": [" source ", "來源", "来源", "從", "从"],
    "targetKeywords": [" target ", "目標", "目标", "到", "向", " into ", " onto ", " to "],
    "directionTokens": [" to ", " into ", " onto ", " -> ", " 到 ", "到", "對齊到", "对齐到"],
    "placementKeywords": ["install", "mount", "place", "put", "attach", "插入", "放進", "放入", "安裝"],
    "targetNameKeywords": [
      "base",
      "ground",
      "floor",
      "table",
      "platform",
      "body",
      "chassis",
      "frame",
      "底座",
      "地面"
    ],
    "llmOverrideKeywords": [
      "install",
      "mount",
      "attach",
      "insert",
      "cover",
      "lid",
      "cap",
      "close",
      "put",
      "place",
      "fit into",
      "fit on",
      "plug",
      "socket",
      "screw",
      "bolt",
      "安裝",
      "裝上",
      "插入",
      "放上",
      "放進",
      "放入",
      "蓋上",
      "蓋起來",
      "套上",
      "鎖上",
      "卡入",
      "插槽",
      "蓋子"
    ]
  },
  "environments": [
    { "alias": "warehouse", "environment": "warehouse" },
    { "alias": "倉庫", "environment": "warehouse" },
    { "alias": "仓库", "environment": "warehouse" },
    { "alias": "studio", "environment": "studio" },
    { "alias": "工作室", "environment": "studio" },
    { "alias": "city", "environment": "city" },
    { "alias": "城市", "environment": "city" },
    { "alias": "sunset", "environment": "sunset" },
    { "alias": "黃昏", "environment": "sunset" },
    { "alias": "黄昏", "environment": "sunset" },
    { "alias": "dawn", "environment": "dawn" },
    { "alias": "清晨", "environment": "dawn" },
    { "alias": "night", "environment": "night" },
    { "alias": "夜晚", "environment": "night" },
    { "alias": "forest", "environment": "forest" },
    { "alias": "森林", "environment": "forest" },
    { "alias": "apartment", "environment": "apartment" },
    { "alias": "公寓", "environment": "apartment" },
    { "alias": "lobby", "environment": "lobby" },
    { "alias": "大廳", "environment": "lobby" },
    { "alias": "大厅", "environment": "lobby" },
    { "alias": "park", "environment": "park" },
    { "alias": "公園", "environment": "park" },
    { "alias": "公园", "environment": "park" }
  ],
  "interactionModes": {
    "rotate": ["rotate", "旋轉", "旋转", "轉動", "转动"],
    "move": ["move", "移動", "移动", "平移"],
    "mate": ["mate", "對齊", "对齐", "組裝", "组装", "裝配", "装配"],
    "select": ["select mode", "選取模式", "选择模式"]
  },
  "generalQuestionTokens": ["請問", "可否", "能不能", "是不是", "是否"],
  "stepCommandRegex": "(?:新增\\\\s*step|add step|create step|new step)\\\\s+(.+)"
}
